LICENSE
MANIFEST.in
README.md
requirements.txt
setup.py
test-requirements.txt
docker/__init__.py
docker/client.py
docker/constants.py
docker/errors.py
docker/tls.py
docker/version.py
docker/auth/__init__.py
docker/auth/auth.py
docker/ssladapter/__init__.py
docker/ssladapter/ssladapter.py
docker/unixconn/__init__.py
docker/unixconn/unixconn.py
docker/utils/__init__.py
docker/utils/decorators.py
docker/utils/types.py
docker/utils/utils.py
docker/utils/ports/__init__.py
docker/utils/ports/ports.py
docker_py_paetling.egg-info/PKG-INFO
docker_py_paetling.egg-info/SOURCES.txt
docker_py_paetling.egg-info/dependency_links.txt
docker_py_paetling.egg-info/not-zip-safe
docker_py_paetling.egg-info/pbr.json
docker_py_paetling.egg-info/requires.txt
docker_py_paetling.egg-info/top_level.txt
tests/__init__.py
tests/base.py
tests/fake_api.py
tests/fake_stat.py
tests/integration_test.py
tests/test.py
tests/utils_test.py